timelyOSC.py
timelyOSC-13.dist-info/COPYING
timelyOSC-13.dist-info/METADATA
timelyOSC-13.dist-info/WHEEL
timelyOSC-13.dist-info/top_level.txt
timelyOSC-13.dist-info/RECORD
