Metadata-Version: 2.1
Name: timelyOSC
Version: 13
Summary: Open Sound Control library for Python 3
Home-page: https://github.com/combatopera/timelyOSC
Author: Andrzej Cichocki
Author-email: 3613868+combatopera@users.noreply.github.com
License-File: COPYING
